{
"type": "FeatureCollection",
"name": "S_STN_START",
"crs": { "type": "name", "properties": { "name": "urn:ogc:def:crs:OGC:1.3:CRS84" } },
"features": [
{ "type": "Feature", "properties": { "DFIRM_ID": "51091C", "VERSION_ID": "1.1.1.0", "START_ID": "1556782_1", "START_DESC": "FEET ABOVE CORPORATE LIMITS", "LOC_ACC": "Low", "SOURCE_CIT": null }, "geometry": { "type": "Point", "coordinates": [ -79.568604580588541, 38.36232799953487 ] } }
]
}
