{
"type": "FeatureCollection",
"name": "S_STN_START",
"crs": { "type": "name", "properties": { "name": "urn:ogc:def:crs:OGC:1.3:CRS84" } },
"features": [
{ "type": "Feature", "properties": { "DFIRM_ID": "51051C", "VERSION_ID": "1.1.1.0", "START_ID": "10929R2_5", "START_DESC": "DISTANCE IN MILES ABOVE CONFLUENCE WITH RUSSELL PRATER CREEK", "LOC_ACC": "Low", "SOURCE_CIT": null }, "geometry": { "type": "Point", "coordinates": [ -82.350285917546842, 37.125672865657073 ] } },
{ "type": "Feature", "properties": { "DFIRM_ID": "51051C", "VERSION_ID": "1.1.1.0", "START_ID": "10929R2_6", "START_DESC": "DISTANCE IN MILES ABOVE CONFLUENCE WITH OPEN FORK", "LOC_ACC": "Low", "SOURCE_CIT": null }, "geometry": { "type": "Point", "coordinates": [ -82.350285917546842, 37.125672865657073 ] } },
{ "type": "Feature", "properties": { "DFIRM_ID": "51051C", "VERSION_ID": "1.1.1.0", "START_ID": "10929R2_7", "START_DESC": "DISTANCE IN MILES ABOVE CONFLUENCE WITH LEVISA FORK", "LOC_ACC": "Low", "SOURCE_CIT": null }, "geometry": { "type": "Point", "coordinates": [ -82.350285917546842, 37.125672865657073 ] } },
{ "type": "Feature", "properties": { "DFIRM_ID": "51051C", "VERSION_ID": "1.1.1.0", "START_ID": "10929R2_1", "START_DESC": "DISTANCE IN FEET ABOVE LIMIT OF DETAILED STUDY", "LOC_ACC": "Low", "SOURCE_CIT": null }, "geometry": { "type": "Point", "coordinates": [ -82.350285917546842, 37.125672865657073 ] } },
{ "type": "Feature", "properties": { "DFIRM_ID": "51051C", "VERSION_ID": "1.1.1.0", "START_ID": "10929R2_2", "START_DESC": "DISTANCE IN MILES ABOVE CONFLUENCE WITH LICK CREEK", "LOC_ACC": "Low", "SOURCE_CIT": null }, "geometry": { "type": "Point", "coordinates": [ -82.350285917546842, 37.125672865657073 ] } },
{ "type": "Feature", "properties": { "DFIRM_ID": "51051C", "VERSION_ID": "1.1.1.0", "START_ID": "10929R2_3", "START_DESC": "DISTANCE IN MILES ABOVE CONFLUENCE WITH RUSSELL FORK", "LOC_ACC": "Low", "SOURCE_CIT": null }, "geometry": { "type": "Point", "coordinates": [ -82.350285917546842, 37.125672865657073 ] } },
{ "type": "Feature", "properties": { "DFIRM_ID": "51051C", "VERSION_ID": "1.1.1.0", "START_ID": "10929R2_4", "START_DESC": "DISTANCE IN MILES ABOVE CONFLUENCE WITH MCCLURE RIVER", "LOC_ACC": "Low", "SOURCE_CIT": null }, "geometry": { "type": "Point", "coordinates": [ -82.350285917546842, 37.125672865657073 ] } }
]
}
