{
"type": "FeatureCollection",
"name": "S_STN_START",
"crs": { "type": "name", "properties": { "name": "urn:ogc:def:crs:OGC:1.3:CRS84" } },
"features": [
{ "type": "Feature", "properties": { "DFIRM_ID": "510054", "VERSION_ID": "1.1.1.0", "START_ID": "510054_11104R2_1", "START_DESC": "FEET ABOVE CORPORATE LIMITS", "LOC_ACC": "Low", "SOURCE_CIT": "510054_FIS1" }, "geometry": { "type": "Point", "coordinates": [ -77.174689266199437, 38.8843305501073 ] } },
{ "type": "Feature", "properties": { "DFIRM_ID": "510054", "VERSION_ID": "1.1.1.0", "START_ID": "510054_11104R2_2", "START_DESC": "FEET ABOVE CONFLUENCE WITH POTOMAC RIVER", "LOC_ACC": "Low", "SOURCE_CIT": "510054_FIS1" }, "geometry": { "type": "Point", "coordinates": [ -77.174689266199437, 38.8843305501073 ] } }
]
}
