{
"type": "FeatureCollection",
"name": "S_STN_START",
"crs": { "type": "name", "properties": { "name": "urn:ogc:def:crs:OGC:1.3:CRS84" } },
"features": [
{ "type": "Feature", "properties": { "DFIRM_ID": "510065", "VERSION_ID": "1.1.1.0", "START_ID": "1466238_2", "START_DESC": "Stream distance in feet above confluence with Chesapeake Bay", "LOC_ACC": "Low", "SOURCE_CIT": null }, "geometry": { "type": "Point", "coordinates": [ -77.487076742312752, 38.299148433670098 ] } }
]
}
