{
"type": "FeatureCollection",
"name": "S_STN_START",
"crs": { "type": "name", "properties": { "name": "urn:ogc:def:crs:OGC:1.3:CRS84" } },
"features": [
{ "type": "Feature", "properties": { "DFIRM_ID": "51175C", "VERSION_ID": "1.1.1.0", "START_ID": "51175C_1", "START_DESC": "FEET ABOVE CONFLUENCE WITH CHOWAN RIVER", "LOC_ACC": "Low", "SOURCE_CIT": null }, "geometry": { "type": "Point", "coordinates": [ -77.103736783221223, 36.71986714918399 ] } },
{ "type": "Feature", "properties": { "DFIRM_ID": "51175C", "VERSION_ID": "1.1.1.0", "START_ID": "51175C_3", "START_DESC": "FEET ABOVE STATE ROUTE 670", "LOC_ACC": "Low", "SOURCE_CIT": null }, "geometry": { "type": "Point", "coordinates": [ -77.103736783221223, 36.71986714918399 ] } },
{ "type": "Feature", "properties": { "DFIRM_ID": "51175C", "VERSION_ID": "1.1.1.0", "START_ID": "51175C_4", "START_DESC": "FEET ABOVE CONFLUENCE WITH CHOWAN RIVER", "LOC_ACC": "Low", "SOURCE_CIT": null }, "geometry": { "type": "Point", "coordinates": [ -77.103736783221223, 36.71986714918399 ] } },
{ "type": "Feature", "properties": { "DFIRM_ID": "51175C", "VERSION_ID": "1.1.1.0", "START_ID": "51175C_2", "START_DESC": "FEET ABOVE CONFLUENCE WITH CHOWAN RIVER", "LOC_ACC": "Low", "SOURCE_CIT": null }, "geometry": { "type": "Point", "coordinates": [ -77.103736783221223, 36.71986714918399 ] } }
]
}
