{
"type": "FeatureCollection",
"name": "S_STN_START",
"crs": { "type": "name", "properties": { "name": "urn:ogc:def:crs:OGC:1.3:CRS84" } },
"features": [
{ "type": "Feature", "properties": { "DFIRM_ID": "510039", "VERSION_ID": "1.1.1.0", "START_ID": "510039_1", "START_DESC": "DISTANCE MEASURED IN FEET ABOVE CONFLUENCE WITH APPOMATTOX RIVER", "LOC_ACC": "Low", "SOURCE_CIT": null }, "geometry": { "type": "Point", "coordinates": [ -77.396867908022728, 37.265030442975977 ] } },
{ "type": "Feature", "properties": { "DFIRM_ID": "510039", "VERSION_ID": "1.1.1.0", "START_ID": "510039_2", "START_DESC": "DISTANCE MEASURED IN FEET ABOVE CONFLUENCE WITH APPOMATTOX RIVER", "LOC_ACC": "Low", "SOURCE_CIT": null }, "geometry": { "type": "Point", "coordinates": [ -77.396867908022728, 37.265030442975977 ] } },
{ "type": "Feature", "properties": { "DFIRM_ID": "510039", "VERSION_ID": "1.1.1.0", "START_ID": "510039_3", "START_DESC": "DISTANCE MEASURED IN MILES ABOVE MOUTH", "LOC_ACC": "Low", "SOURCE_CIT": null }, "geometry": { "type": "Point", "coordinates": [ -77.396867908022728, 37.265030442975977 ] } }
]
}
